acdctools/__init__.py
acdctools/_core.py
acdctools/_version.py
acdctools/docx.py
acdctools/features.py
acdctools/io.py
acdctools/measure.py
acdctools/path.py
acdctools/plot.py
acdctools/regex.py
acdctools/segmentation.py
acdctools/utils.py
acdctools/widgets.py
acdctools-0.3.dist-info/LICENSE
acdctools-0.3.dist-info/METADATA
acdctools-0.3.dist-info/WHEEL
acdctools-0.3.dist-info/top_level.txt
acdctools-0.3.dist-info/RECORD
